MANIFEST.in
README.rst
setup.py
Megacron.egg-info/PKG-INFO
Megacron.egg-info/SOURCES.txt
Megacron.egg-info/dependency_links.txt
Megacron.egg-info/entry_points.txt
Megacron.egg-info/requires.txt
Megacron.egg-info/top_level.txt
megacron/__init__.py
megacron/api.py
megacron/config.py
megacron/edit.py
megacron/status.py
megacron/conf/megacron.conf
megacron/daemon/__init__.py
megacron/daemon/main.py
megacron/daemon/scheduler.py
megacron/daemon/worker.py