Metadata-Version: 1.0
Name: Megacron
Version: 0.4
Summary: Distributed Cron Replacement
Home-page: https://www.mediawiki.org/wiki/Facebook_Open_Academy/Cron
Author: John Tanner, Favian Contreras, Ben Zeghers
Author-email: megacronteam@gmail.com
License: Creative Commons Attribution-Noncommercial-Share Alike license
Platform: UNKNOWN
